langgraph/checkpoint/redis/__init__.py
langgraph/checkpoint/redis/aio.py
langgraph/checkpoint/redis/ashallow.py
langgraph/checkpoint/redis/base.py
langgraph/checkpoint/redis/jsonplus_redis.py
langgraph/checkpoint/redis/key_registry.py
langgraph/checkpoint/redis/message_exporter.py
langgraph/checkpoint/redis/py.typed
langgraph/checkpoint/redis/shallow.py
langgraph/checkpoint/redis/types.py
langgraph/checkpoint/redis/util.py
langgraph/checkpoint/redis/version.py
langgraph/middleware/__init__.py
langgraph/middleware/redis/__init__.py
langgraph/middleware/redis/aio.py
langgraph/middleware/redis/base.py
langgraph/middleware/redis/composition.py
langgraph/middleware/redis/conversation_memory.py
langgraph/middleware/redis/semantic_cache.py
langgraph/middleware/redis/semantic_router.py
langgraph/middleware/redis/tool_cache.py
langgraph/middleware/redis/types.py
langgraph/middleware/redis/vectorizer.py
langgraph/store/redis/__init__.py
langgraph/store/redis/aio.py
langgraph/store/redis/base.py
langgraph/store/redis/py.typed
langgraph/store/redis/token_unescaper.py
langgraph/store/redis/types.py
langgraph_checkpoint_redis-0.3.3.dist-info/LICENSE
langgraph_checkpoint_redis-0.3.3.dist-info/METADATA
langgraph_checkpoint_redis-0.3.3.dist-info/WHEEL
langgraph_checkpoint_redis-0.3.3.dist-info/entry_points.txt
langgraph_checkpoint_redis-0.3.3.dist-info/RECORD
