Metadata-Version: 2.1
Name: langgraph-checkpoint-redis
Version: 0.3.3
Summary: Redis implementation of the LangGraph agent checkpoint saver and store.
Home-page: https://www.github.com/redis-developer/langgraph-redis
License: MIT
Keywords: ai,redis,redis-client,vector-database,agents,langgraph,langchain
Author: Redis Inc.
Author-email: applied.ai@redis.com
Requires-Python: >=3.10,<3.14
Classifier: License :: OSI Approved :: MIT License
Classifier: Programming Language :: Python :: 3
Classifier: Programming Language :: Python :: 3.10
Classifier: Programming Language :: Python :: 3.11
Classifier: Programming Language :: Python :: 3.12
Classifier: Programming Language :: Python :: 3.13
Requires-Dist: langgraph-checkpoint (>=3.0.0,<4.0.0)
Requires-Dist: orjson (>=3.9.0,<4.0.0)
Requires-Dist: redis (>=5.2.1)
Requires-Dist: redisvl (>=0.11.0,<1.0.0)
Requires-Dist: tomli (>=2.0.1,<3.0.0) ; python_version < "3.11"
Project-URL: Repository, https://www.github.com/redis-developer/langgraph-redis
